scraper_4_email/__init__.py
scraper_4_email/cli.py
scraper_4_email/scraper.py
scraper_4_email-0.1.0.dist-info/licenses/LICENSE
scraper_4_email-0.1.0.dist-info/METADATA
scraper_4_email-0.1.0.dist-info/WHEEL
scraper_4_email-0.1.0.dist-info/entry_points.txt
scraper_4_email-0.1.0.dist-info/top_level.txt
scraper_4_email-0.1.0.dist-info/RECORD
