Metadata-Version: 2.4
Name: scraper-4-email
Version: 0.1.0
Summary: Scrape e-mails from Excel files on websites.
Author: Franck da COSTA
Classifier: Programming Language :: Python :: 3
Classifier: Operating System :: OS Independent
Requires-Python: >=3.7
License-File: LICENSE
Requires-Dist: requests
Requires-Dist: beautifulsoup4
Requires-Dist: pandas
Requires-Dist: openpyxl
Dynamic: author
Dynamic: classifier
Dynamic: license-file
Dynamic: requires-dist
Dynamic: requires-python
Dynamic: summary
